{
  "30대": {
    "직장스트레스": [
      {
        "감정공감": "매일 반복되는 업무 압박 속에서 정말 많이 지치셨겠어요. 열심히 하는데도 끝이 보이지 않는 느낌, 충분히 힘드실 수 있어요.",
        "상황분석": "30대 직장인은 성과 압박과 커리어 불안이 동시에 오는 시기예요. 지금 느끼는 스트레스는 의지 부족이 아니라 구조적인 문제일 수 있어요.",
        "관점전환": "가족 눈에 비친 당신은 어떤 모습일까요? 매일 지쳐서 들어오는 모습을 보며 가족은 말 못하고 걱정하고 있을 거예요. 힘들다고 말해주는 것만으로도 가족에게 큰 위안이 돼요.",
        "행동제안": "오늘 퇴근 후 딱 10분만 걷기를 해보세요. 회사 밖 공기를 마시는 것만으로도 머릿속이 조금 정리될 거예요.",
        "희망메시지": "지금 버티고 있는 것 자체가 대단한 거예요. 조금씩 나아지고 있어요."
      },
      {
        "감정공감": "직장에서의 스트레스가 집까지 따라오는 느낌, 어디서도 온전히 쉬지 못하는 그 답답함이 느껴져요.",
        "상황분석": "30대는 '이 정도면 버텨야 하지 않나'라는 압박이 특히 강한 시기예요. 하지만 지속되는 스트레스는 반드시 출구가 필요해요.",
        "관점전환": "5년 후의 당신이 지금을 돌아본다면 뭐라고 할까요? 그때의 내가 지금 나에게 해줄 말을 생각해보세요.",
        "행동제안": "오늘 퇴근길에 좋아하는 음악 한 곡을 들으며 천천히 걸어보세요. 이동 시간을 나만의 전환 의식으로 만들어봐요.",
        "희망메시지": "힘들다고 느끼는 것 자체가 아직 포기하지 않았다는 증거예요. 충분히 잘하고 있어요."
      },
      {
        "감정공감": "열심히 했는데 인정받지 못하는 느낌, 그 허탈함은 단순한 피로와는 달라요. 진짜 힘드셨겠어요.",
        "상황분석": "직장 스트레스의 핵심은 종종 '통제감 상실'이에요. 내가 아무리 해도 달라지지 않는다는 느낌이 가장 소진감을 높여요.",
        "관점전환": "지금 함께 일하는 동료 중에도 비슷한 감정을 느끼는 분이 있을 거예요. 혼자가 아니라는 걸 기억해요.",
        "행동제안": "오늘 한 가지, 내가 통제할 수 있는 작은 일을 완성해보세요. 책상 정리도 좋아요. 완성의 감각이 에너지를 돌려줘요.",
        "희망메시지": "이 시기가 영원히 계속되지는 않아요. 지금 이 경험이 당신을 더 단단하게 만들고 있어요."
      }
    ],
    "번아웃": [
      {
        "감정공감": "아무것도 하기 싫고 무기력한 느낌, 그게 바로 번아웃이에요. 당신이 나약한 게 아니에요.",
        "상황분석": "번아웃은 오랫동안 자신을 돌보지 않고 달려온 결과예요. 몸과 마음이 이제 쉬어야 한다는 신호를 보내고 있는 거예요.",
        "관점전환": "지금 쉬는 것도 성장의 일부예요. 달리기 선수도 회복 없이는 더 빨리 달릴 수 없어요. 주변 사람들도 당신이 쉬기를 바라고 있을 거예요.",
        "행동제안": "이번 주말 딱 하루, 아무 계획 없이 쉬어보세요. 아무것도 안 해도 괜찮아요.",
        "희망메시지": "지금 쉬는 것도 성장의 일부예요. 충분히 잘하고 있어요."
      },
      {
        "감정공감": "모든 게 의미 없게 느껴지고, 아침에 일어나는 것조차 힘들어진 그 느낌. 그 무게가 얼마나 무거울지 충분히 공감해요.",
        "상황분석": "번아웃은 갑자기 오지 않아요. 오랫동안 자신의 신호를 무시하고 달려온 결과예요. 이제 몸이 멈추라고 말하는 거예요.",
        "관점전환": "가장 가까운 사람에게 지금 이 상태를 솔직하게 말해본 적 있나요? 혼자 감당하려 하지 않아도 돼요.",
        "행동제안": "오늘 하루 딱 한 가지 작은 즐거움을 찾아보세요. 좋아하는 음식, 좋아하는 냄새, 좋아하는 장소 하나만.",
        "희망메시지": "번아웃을 느낀다는 건 그동안 정말 열심히 살았다는 뜻이에요. 이제 자신을 돌볼 차례예요."
      },
      {
        "감정공감": "일도, 사람도, 모든 것에서 도망치고 싶은 마음. 그 탈진의 감각, 너무 잘 알 것 같아요.",
        "상황분석": "30대 번아웃은 성취 욕구와 현실의 간극에서 오는 경우가 많아요. 열심히 했는데 채워지지 않는 무언가가 있을 때 찾아와요.",
        "관점전환": "지금 당신에게 필요한 건 더 열심히 하는 게 아니라 멈추는 용기예요. 쉬는 것도 선택이고 그 선택은 옳아요.",
        "행동제안": "이번 주말 자연 속으로 나가보세요. 숲길 30분이 일주일치 피로를 녹여주기도 해요.",
        "희망메시지": "회복하는 당신이 더 강해질 거예요. 지금 이 쉼이 다음 도약의 시작이에요."
      }
    ],
    "육아": [
      {
        "감정공감": "일과 육아를 동시에 감당하는 건 정말 슈퍼맨도 힘든 일이에요. 지치는 게 당연해요.",
        "상황분석": "30대 육아는 커리어와 가정 사이에서 끊임없는 선택을 요구해요. 어느 쪽도 포기할 수 없는 그 무게가 쌓여있을 거예요.",
        "관점전환": "아이 눈에 비친 엄마/아빠는 세상에서 가장 멋진 사람이에요. 완벽하지 않아도 곁에 있어주는 것만으로 충분해요.",
        "행동제안": "오늘 아이와 딱 15분만 핸드폰 없이 눈을 맞춰보세요. 그 15분이 아이에게는 하루 전부가 될 수 있어요.",
        "희망메시지": "완벽한 부모가 아니어도 괜찮아요. 사랑하는 마음이 있다면 충분해요."
      },
      {
        "감정공감": "육아는 24시간 끊임없는 헌신이에요. 지쳐도 내색하기 힘든 그 마음, 충분히 이해해요.",
        "상황분석": "부모도 사람이에요. 지치고 힘들고 도망가고 싶을 때가 있어요. 그 감정을 느끼는 것 자체가 나쁜 부모의 증거가 아니에요.",
        "관점전환": "아이는 완벽한 부모보다 행복한 부모를 원해요. 내가 먼저 채워져야 아이에게도 줄 수 있어요.",
        "행동제안": "오늘 배우자나 가족에게 솔직하게 말해보세요. '나 좀 쉬어야 할 것 같아'라는 한 마디가 큰 도움을 불러올 수 있어요.",
        "희망메시지": "지금 이 힘든 시기가 지나면 아이와 함께한 이 순간들이 가장 소중한 기억이 될 거예요."
      },
      {
        "감정공감": "아이를 사랑하면서도 때로는 모든 걸 내려놓고 싶은 그 복잡한 감정, 죄책감 없이 느껴도 괜찮아요.",
        "상황분석": "일하는 부모는 항상 어딘가에서 죄책감을 느껴요. 직장에선 부모로서, 집에선 직장인으로서. 이 구조적인 갈등은 당신의 잘못이 아니에요.",
        "관점전환": "아이는 엄마/아빠가 행복할 때 더 행복해요. 나를 위한 시간이 결국 아이를 위한 시간이에요.",
        "행동제안": "이번 주 단 한 시간만 나만의 시간을 만들어보세요. 아이에게도 혼자만의 시간이 필요하듯 부모도 마찬가지예요.",
        "희망메시지": "최선을 다하고 있는 당신은 이미 충분히 좋은 부모예요."
      }
    ],
    "인간관계": [
      {
        "감정공감": "직장에서의 인간관계 스트레스는 업무보다 더 지치게 만들 수 있어요. 그 피로감 충분히 이해해요.",
        "상황분석": "30대는 다양한 관계 속에서 자신의 위치를 찾아가는 시기예요. 모든 관계를 잘 유지하려는 압박이 오히려 더 힘들게 만들 수 있어요.",
        "관점전환": "상대방도 나름의 스트레스와 사정이 있을 거예요. 모든 관계를 완벽하게 유지할 필요는 없어요.",
        "행동제안": "나와 잘 맞는 한 명에게 먼저 연락해보세요. 좋은 관계 하나가 열 개의 힘든 관계를 버티게 해줘요.",
        "희망메시지": "모든 사람과 잘 지낼 필요는 없어요. 진짜 내 편 한 명이면 충분해요."
      },
      {
        "감정공감": "사람 때문에 상처받고, 또 사람 때문에 버티는 게 인간관계의 역설이에요. 그 피로가 느껴져요.",
        "상황분석": "30대는 관계의 양보다 질이 중요해지는 시기예요. 모든 관계를 유지하려다 정작 중요한 관계를 소홀히 할 수 있어요.",
        "관점전환": "지금 힘들게 하는 그 사람도, 본인만의 사정과 상처가 있을 거예요. 이해가 되지 않더라도 그 사람도 최선을 다하고 있을 거예요.",
        "행동제안": "오늘 한 사람과의 관계에서 기대치를 조금 낮춰보세요. 기대가 줄면 실망도 줄어요.",
        "희망메시지": "좋은 관계는 만들어지는 게 아니라 쌓이는 거예요. 천천히 가도 괜찮아요."
      },
      {
        "감정공감": "관계 때문에 소진되는 느낌, 어디서도 있는 그대로의 나를 보여줄 수 없다는 외로움이 느껴져요.",
        "상황분석": "직장 내 인간관계는 내가 선택한 관계가 아니에요. 어쩔 수 없이 함께해야 하는 상황 자체가 스트레스의 원인이에요.",
        "관점전환": "직장 동료와 친구가 되지 않아도 괜찮아요. 전문적으로 협력하면서 적당한 거리를 유지하는 것도 건강한 관계예요.",
        "행동제안": "퇴근 후 직장 관련 연락은 잠시 끊어보세요. 업무 시간 외에는 나만의 경계를 만들어요.",
        "희망메시지": "당신의 에너지는 소중해요. 진짜 중요한 사람들에게 쓰세요."
      }
    ],
    "미래불안": [
      {
        "감정공감": "30대에 미래가 불안한 건 너무나 자연스러운 감정이에요. 불안하다는 건 그만큼 삶을 진지하게 생각한다는 뜻이에요.",
        "상황분석": "30대는 커리어, 결혼, 재테크 등 큰 결정들이 몰려오는 시기예요. 모든 것을 한 번에 해결하려 하면 더 힘들어질 수 있어요.",
        "관점전환": "10년 후의 당신이 지금 이 시간을 돌아본다면 어떻게 볼까요? 지금 고민하고 있다는 것 자체가 이미 잘 살고 있다는 증거예요.",
        "행동제안": "오늘 딱 한 가지만 결정해보세요. 작은 결정들이 쌓여 큰 방향이 만들어져요.",
        "희망메시지": "불안은 성장의 신호예요. 지금 이 고민이 더 나은 내일을 만들고 있어요."
      },
      {
        "감정공감": "또래들과 나를 비교하며 뒤처지는 것 같은 느낌, 그 불안이 얼마나 크게 느껴지는지 알아요.",
        "상황분석": "SNS 시대의 비교는 30대를 가장 힘들게 해요. 하지만 보이는 것이 전부가 아니에요. 모두가 각자의 방식으로 불안을 품고 살아가고 있어요.",
        "관점전환": "당신의 타이밍은 다른 사람의 타이밍이 아니에요. 남들보다 늦어도 당신에게 맞는 때가 있어요.",
        "행동제안": "오늘 SNS를 하루만 쉬어보세요. 비교의 창을 닫으면 불안이 조금 줄어들어요.",
        "희망메시지": "늦은 것이 아니라 당신만의 속도로 가고 있는 거예요."
      },
      {
        "감정공감": "미래가 안 보이는 것 같은 그 막막함, 어디서부터 시작해야 할지 모르는 답답함이 느껴져요.",
        "상황분석": "미래 불안의 상당 부분은 불확실성에서 와요. 모든 것을 미리 알 수 없다는 사실 자체가 불안을 만들어요.",
        "관점전환": "지금 당신이 가진 것들을 한번 써보세요. 건강, 경험, 관계, 능력. 이미 가진 것들이 생각보다 많을 거예요.",
        "행동제안": "오늘 1년 후 내가 되고 싶은 모습을 딱 세 줄만 써보세요. 방향이 생기면 불안이 조금 줄어들어요.",
        "희망메시지": "불확실한 미래를 걱정하는 것보다 오늘을 충실히 사는 것이 가장 확실한 미래 준비예요."
      }
    ]
  },
  "40대": {
    "직장스트레스": [
      {
        "감정공감": "중간관리자로서 위아래 모두를 챙겨야 하는 그 무게감, 정말 힘드셨겠어요.",
        "상황분석": "40대 직장인은 조직의 허리 역할을 하면서 가장 많은 압박을 받는 시기예요. 위에서도 아래에서도 치이는 구조적인 어려움이에요.",
        "관점전환": "팀원들 눈에 당신은 든든한 버팀목으로 보일 거예요. 그 역할이 쉽지 않다는 걸 주변도 알고 있어요.",
        "행동제안": "오늘 팀원 중 한 명에게 '수고했어요' 한 마디를 건네보세요. 주는 따뜻함이 나에게도 돌아와요.",
        "희망메시지": "지금 버티고 있는 것 자체가 리더십이에요. 충분히 잘하고 있어요."
      },
      {
        "감정공감": "성과 압박과 팀 관리를 동시에 해야 하는 40대 직장인의 무게, 정말 쉽지 않다는 거 알아요.",
        "상황분석": "40대는 경험은 풍부하지만 체력은 줄어드는 아이러니한 시기예요. 더 많은 걸 알기 때문에 더 많은 걸 걱정하게 돼요.",
        "관점전환": "20년의 경험이 있는 당신은 어떤 신입도 따라올 수 없는 강점이 있어요. 그 가치를 스스로 인정해보세요.",
        "행동제안": "오늘 퇴근 후 동료나 친구에게 연락해보세요. 같은 처지의 이야기를 나누는 것만으로도 큰 위안이 돼요.",
        "희망메시지": "당신의 경험과 내공은 어느 누구도 쉽게 쌓을 수 없는 자산이에요."
      },
      {
        "감정공감": "열심히 해왔는데도 여전히 힘든 것 같은 그 허탈감, 40대라면 더욱 복잡하게 느껴질 거예요.",
        "상황분석": "40대 직장 스트레스는 단순한 업무 과부하가 아니에요. 정체성과 방향성에 대한 고민이 함께 오는 경우가 많아요.",
        "관점전환": "지금 하는 일이 나에게 맞는지 진지하게 생각해본 적 있나요? 불편함이 때로는 변화의 신호일 수 있어요.",
        "행동제안": "이번 주말 혼자만의 시간을 내어 '내가 정말 원하는 것'에 대해 조용히 생각해보세요.",
        "희망메시지": "40대는 새로운 방향을 모색하기에 충분히 이른 나이예요."
      }
    ],
    "부모부양": [
      {
        "감정공감": "부모님을 부양하면서 자녀도 키우는 이중 부담, 정말 많이 지치셨겠어요.",
        "상황분석": "40대 샌드위치 세대는 위로는 부모님, 아래로는 자녀를 동시에 책임져야 해요. 이건 개인의 문제가 아니라 세대 전체가 겪는 구조적인 어려움이에요.",
        "관점전환": "부모님 눈에 당신은 최고의 자녀예요. 완벽하게 챙기지 못해도 곁에 있어주는 것만으로 부모님은 행복하실 거예요.",
        "행동제안": "이번 주말 부모님께 짧은 안부 전화 한 통 해보세요. 긴 말 없이 목소리만 들어도 서로에게 위안이 돼요.",
        "희망메시지": "두 세대를 잇는 당신의 역할이 가족을 하나로 묶고 있어요."
      },
      {
        "감정공감": "내 것을 챙기기도 버거운데 부모님까지 걱정해야 하는 그 무게, 혼자 짊어지기엔 너무 무거워요.",
        "상황분석": "부모 부양은 경제적 부담뿐 아니라 정서적 에너지도 많이 소비해요. 특히 40대는 자신의 미래도 준비해야 하는 시기라 더욱 복잡해요.",
        "관점전환": "형제자매가 있다면 역할을 나눠볼 수 있어요. 혼자 다 하려 하지 않아도 괜찮아요. 도움을 요청하는 것도 효도의 방법이에요.",
        "행동제안": "오늘 가족과 부모님 부양에 대한 솔직한 대화를 시작해보세요. 혼자 감당하지 않아도 되는 방법을 함께 찾아봐요.",
        "희망메시지": "부모님을 걱정하는 그 마음이 이미 훌륭한 자녀의 증거예요."
      },
      {
        "감정공감": "부모님이 아프시거나 돌봄이 필요할 때의 그 걱정과 부담감, 말로 다 표현하기 어려운 감정이에요.",
        "상황분석": "나이 드신 부모님을 돌보는 것은 체력과 감정 모두를 소진시켜요. 이 상황에서 지치는 것은 당연하고 자연스러운 반응이에요.",
        "관점전환": "지금 당신이 부모님께 해드리는 모든 것들, 부모님은 그 마음을 느끼고 계실 거예요. 완벽하게 하지 않아도 충분해요.",
        "행동제안": "주변의 돌봄 서비스나 지원 제도를 알아보세요. 혼자 모든 것을 해결하려 하지 않아도 돼요.",
        "희망메시지": "당신이 하고 있는 것들이 부모님께는 세상 전부예요."
      }
    ],
    "번아웃": [
      {
        "감정공감": "모든 걸 내려놓고 싶은 그 마음, 충분히 이해해요. 정말 오래 달려오셨어요.",
        "상황분석": "40대 번아웃은 20~30대와 달리 회복이 더 필요해요. 몸과 마음이 함께 쉬어야 하는 시기예요.",
        "관점전환": "배우자와 자녀 눈에 지금 당신이 얼마나 지쳐 보이는지 알고 있을까요? 내가 쉬어야 가족도 더 행복해요.",
        "행동제안": "이번 주말 가족과 함께 가까운 산책로를 걸어보세요. 함께하는 시간이 번아웃 회복에 가장 좋은 약이에요.",
        "희망메시지": "쉬는 것도 가족을 위한 일이에요. 지금 멈춰도 괜찮아요."
      },
      {
        "감정공감": "20년 가까이 달려왔는데 이제 더 이상 달릴 힘이 없는 것 같은 느낌, 그 소진감이 느껴져요.",
        "상황분석": "40대 번아웃의 특징은 '이제 뭘 위해 하나'라는 의문이 함께 온다는 거예요. 방향 상실감이 피로를 더욱 무겁게 만들어요.",
        "관점전환": "지금 멈추는 것이 포기가 아니에요. 더 오래, 더 잘 가기 위한 필수적인 정지예요.",
        "행동제안": "오늘 아무것도 하지 않는 시간을 일부러 만들어보세요. 아무것도 안 하는 것도 능력이에요.",
        "희망메시지": "번아웃이 온다는 건 그만큼 열심히 살았다는 증거예요. 이제 나를 돌볼 차례예요."
      },
      {
        "감정공감": "의욕도 없고 재미도 없고 그냥 하루하루 버티는 느낌, 그 무기력함이 얼마나 힘든지 알아요.",
        "상황분석": "40대 번아웃은 종종 '내가 원하는 게 뭔지 모르겠다'는 상실감을 동반해요. 오래 남을 위해 달려왔기 때문이에요.",
        "관점전환": "20대의 당신이 좋아했던 것들을 떠올려보세요. 그때의 열정이 어디로 갔는지 찾아보는 게 회복의 시작이 될 수 있어요.",
        "행동제안": "오랫동안 하고 싶었지만 못 했던 것 하나를 이번 주 해보세요. 작은 것도 좋아요.",
        "희망메시지": "당신 안에 아직 불씨가 있어요. 조금만 바람을 불어넣으면 다시 타오를 거예요."
      }
    ],
    "자녀교육": [
      {
        "감정공감": "자녀 교육에 대한 걱정과 압박, 부모라면 누구나 느끼는 감정이에요. 혼자 감당하려 하지 않아도 돼요.",
        "상황분석": "40대는 자녀의 중요한 시기와 맞물려 교육 스트레스가 극대화되는 때예요. 내 아이를 위한 마음이 클수록 부담도 커지는 게 당연해요.",
        "관점전환": "자녀 눈에 부모의 잔소리는 사랑이에요. 하지만 때로는 그냥 옆에 앉아있는 것만으로도 충분해요.",
        "행동제안": "오늘 저녁 공부 이야기 말고 아이가 좋아하는 주제로 10분 대화해보세요.",
        "희망메시지": "좋은 부모가 되려는 그 마음 자체가 이미 좋은 부모의 증거예요."
      },
      {
        "감정공감": "아이가 잘 되기를 바라는 마음이 클수록 불안도 커지는 그 감정, 충분히 이해해요.",
        "상황분석": "자녀 교육 스트레스의 핵심은 종종 '비교'에서 시작돼요. 남의 아이와 내 아이를 비교하는 순간 불안이 증폭돼요.",
        "관점전환": "아이는 부모의 불안을 그대로 흡수해요. 내가 먼저 평온해져야 아이도 편안해져요.",
        "행동제안": "오늘 아이에게 '넌 지금 이대로 충분해'라고 말해주세요. 그 말이 아이에게 가장 큰 교육이에요.",
        "희망메시지": "아이의 속도를 믿어주세요. 당신의 아이는 당신만의 방식으로 잘 자라고 있어요."
      },
      {
        "감정공감": "내 아이가 혹시 뒤처지는 건 아닐까 하는 그 조바심, 부모라면 누구나 느끼는 감정이에요.",
        "상황분석": "지금 시대의 교육 환경은 부모도 아이도 모두 힘들게 만들어요. 이건 개인의 문제가 아니라 시스템의 문제예요.",
        "관점전환": "10년 후 아이에게 가장 필요한 것은 성적이 아니라 스스로 생각하고 도전하는 힘이에요. 지금 그 힘을 키우는 중이에요.",
        "행동제안": "이번 주말 아이와 공부 말고 함께 즐길 수 있는 무언가를 해보세요. 그 시간이 더 큰 교육이에요.",
        "희망메시지": "아이를 믿는 부모의 믿음이 아이를 가장 크게 성장시켜요."
      }
    ],
    "건강관리": [
      {
        "감정공감": "바쁜 일상 속에서 내 몸을 챙기지 못하는 죄책감, 40대라면 더욱 크게 느껴지죠.",
        "상황분석": "40대는 몸의 변화를 실감하기 시작하는 시기예요. 건강에 신경 쓰이기 시작했다는 것 자체가 좋은 신호예요.",
        "관점전환": "가족들은 당신이 건강하게 오래 곁에 있어주기를 바라고 있어요. 나를 위한 건강 관리가 가족을 위한 일이기도 해요.",
        "행동제안": "오늘 점심 후 10분 걷기부터 시작해보세요. 작은 습관이 큰 변화를 만들어요.",
        "희망메시지": "지금 시작하는 게 가장 빠른 거예요. 오늘부터가 새 시작이에요."
      },
      {
        "감정공감": "몸이 예전 같지 않다는 걸 느끼면서도 바쁘다는 핑계로 미루게 되는 그 마음, 충분히 이해해요.",
        "상황분석": "40대는 체력 저하가 시작되지만 할 일은 오히려 늘어나는 시기예요. 건강 관리를 미루면 나중에 더 큰 대가를 치르게 돼요.",
        "관점전환": "건강에 투자하는 시간은 낭비가 아니에요. 가장 중요한 일을 위한 준비예요.",
        "행동제안": "오늘 당장 건강검진 예약을 해보세요. 아는 것이 힘이에요. 현재 상태를 파악하는 것이 시작이에요.",
        "희망메시지": "지금 챙기는 건강이 10년 후의 당신을 만들어요."
      },
      {
        "감정공감": "건강 걱정은 되는데 어디서부터 어떻게 시작해야 할지 모르는 막막함, 느껴져요.",
        "상황분석": "40대 건강 관리의 핵심은 완벽한 루틴이 아니라 꾸준한 작은 습관이에요. 한 번에 다 바꾸려 하면 오히려 포기하게 돼요.",
        "관점전환": "가족과 함께하는 건강 활동을 만들어보세요. 혼자 하는 것보다 함께 하면 더 오래 지속할 수 있어요.",
        "행동제안": "오늘 저녁 가족과 함께 30분 산책을 해보세요. 건강도 챙기고 대화도 나눌 수 있어요.",
        "희망메시지": "건강을 생각하기 시작했다는 것 자체가 이미 좋은 변화의 시작이에요."
      }
    ]
  },
  "50대": {
    "은퇴준비": [
      {
        "감정공감": "은퇴를 앞두고 느끼는 막막함, 오랫동안 달려온 분이라면 더욱 크게 느껴지실 거예요.",
        "상황분석": "은퇴 불안은 준비가 부족해서가 아니에요. 삶의 방향이 바뀌는 큰 전환점 앞에서 느끼는 자연스러운 감정이에요.",
        "관점전환": "배우자 눈에 당신의 고민이 보일 거예요. 함께 은퇴 후 삶을 그려보는 대화가 둘 다에게 위안이 될 수 있어요.",
        "행동제안": "이번 주말 귀농 체험 프로그램에 한 번 가보세요. 직접 경험해보면 막연한 불안이 구체적인 계획으로 바뀔 거예요.",
        "희망메시지": "인생 2막은 준비된 사람에게 더 풍요로워요. 이미 시작하고 있어요."
      },
      {
        "감정공감": "30년 가까이 일해왔는데 갑자기 멈춰야 한다는 것, 그 공백이 얼마나 클지 충분히 느껴져요.",
        "상황분석": "은퇴 후 정체성 상실은 많은 분들이 경험해요. 일이 삶의 큰 부분을 차지했다면 더욱 그럴 수 있어요. 하지만 새로운 정체성을 만들 시간이 충분히 있어요.",
        "관점전환": "은퇴는 끝이 아니라 다른 시작이에요. 하고 싶었지만 못 했던 것들을 할 수 있는 기회예요.",
        "행동제안": "은퇴 후 하고 싶은 것들을 리스트로 만들어보세요. 10개 이상 써보세요. 생각보다 많을 거예요.",
        "희망메시지": "당신의 경험과 지혜는 은퇴 후에 오히려 더 빛날 수 있어요."
      },
      {
        "감정공감": "재정적인 걱정과 막연한 미래 불안이 겹쳐지는 그 복잡한 마음, 충분히 이해해요.",
        "상황분석": "은퇴 준비는 재정만의 문제가 아니에요. 관계, 건강, 취미, 의미 등 삶 전체를 다시 설계해야 하는 큰 작업이에요.",
        "관점전환": "지금까지 잘 살아오셨어요. 은퇴 후에도 그 지혜로 잘 헤쳐나가실 수 있어요.",
        "행동제안": "은퇴 후 삶에 대해 비슷한 상황의 친구나 선배와 이야기를 나눠보세요. 그들의 경험이 큰 도움이 될 거예요.",
        "희망메시지": "은퇴를 준비한다는 것 자체가 이미 현명한 선택이에요."
      }
    ],
    "인간관계": [
      {
        "감정공감": "오랜 시간 쌓아온 관계들이 흔들릴 때의 허탈함, 정말 힘드셨겠어요.",
        "상황분석": "50대는 관계의 질을 다시 생각하게 되는 시기예요. 많은 관계보다 진짜 관계 하나가 더 소중해지는 때예요.",
        "관점전환": "상대방도 나름의 변화와 고민 속에 있을 거예요. 먼저 손을 내밀면 관계가 다시 따뜻해질 수 있어요.",
        "행동제안": "오래 연락 못한 소중한 사람 한 명에게 먼저 연락해보세요.",
        "희망메시지": "진짜 관계는 시간이 지나도 다시 이어져요. 지금 시작해도 늦지 않아요."
      },
      {
        "감정공감": "나이가 들수록 사람 관계가 더 어렵게 느껴지는 그 아이러니, 충분히 공감해요.",
        "상황분석": "50대는 은퇴나 자녀 독립 등으로 자연스럽게 관계망이 좁아지는 시기예요. 이것은 변화이지 실패가 아니에요.",
        "관점전환": "지금은 관계를 넓히기보다 깊게 하는 시기예요. 적어도 한 명의 진짜 친구가 수십 명의 지인보다 값져요.",
        "행동제안": "오랫동안 만나지 못한 소중한 분과 만남을 잡아보세요. 식사 한 끼가 오랜 추억을 다시 이어줄 거예요.",
        "희망메시지": "50대의 우정은 더 깊고 진해요. 지금 새로운 인연도 충분히 가능해요."
      },
      {
        "감정공감": "서로 이해하기 어려운 사람들과의 관계에서 오는 피로감, 50대라면 더욱 복잡하게 느껴질 거예요.",
        "상황분석": "세대 간 소통의 어려움, 오랜 관계에서 오는 갈등, 새로운 관계 형성의 부담이 50대 인간관계의 과제예요.",
        "관점전환": "모든 관계가 편할 수는 없어요. 어떤 관계는 거리를 두는 것이 서로에게 더 좋을 수 있어요.",
        "행동제안": "나에게 에너지를 주는 관계와 빼앗는 관계를 솔직하게 구분해보세요. 에너지를 주는 관계에 더 집중해요.",
        "희망메시지": "좋은 관계는 억지로 유지하는 게 아니에요. 자연스럽게 맞는 관계가 남아있을 거예요."
      }
    ],
    "건강관리": [
      {
        "감정공감": "몸의 변화를 느끼기 시작할 때의 불안함, 충분히 이해해요.",
        "상황분석": "50대는 몸이 관리를 요청하는 시기예요. 신호를 무시하지 않고 들어주는 것이 가장 현명한 선택이에요.",
        "관점전환": "가족들은 당신이 건강하게 오래 곁에 있어주기를 바라고 있어요. 나를 위한 건강 관리가 가족을 위한 사랑이에요.",
        "행동제안": "이번 주 숲속 산책 프로그램에 참여해보세요. 자연 속 걷기가 몸과 마음을 동시에 치유해요.",
        "희망메시지": "지금 관리를 시작하는 게 가장 현명한 투자예요."
      },
      {
        "감정공감": "아프면 안 된다는 부담감과 몸이 말을 안 듣는 현실 사이의 갈등, 충분히 공감해요.",
        "상황분석": "50대의 건강은 20~30대처럼 저절로 회복되지 않아요. 적극적인 관리가 필요한 시기예요.",
        "관점전환": "건강을 챙기는 것은 이기적인 게 아니에요. 내가 건강해야 가족과 주변 사람들을 더 잘 돌볼 수 있어요.",
        "행동제안": "정기 검진을 통해 현재 건강 상태를 정확히 파악해보세요. 아는 것이 불안보다 나아요.",
        "희망메시지": "건강을 챙기기 시작하는 지금이 가장 좋은 때예요."
      },
      {
        "감정공감": "운동해야 하는 걸 알면서도 시작이 어려운 그 마음, 충분히 이해해요.",
        "상황분석": "50대 건강 관리의 핵심은 무리하지 않는 꾸준함이에요. 격렬한 운동보다 매일 조금씩이 훨씬 효과적이에요.",
        "관점전환": "건강한 50대는 더 활기찬 60대, 70대로 이어져요. 지금의 투자가 미래의 삶의 질을 결정해요.",
        "행동제안": "오늘 저녁 동네 한 바퀴만 걸어보세요. 20분이면 충분해요. 그 작은 시작이 큰 변화를 만들어요.",
        "희망메시지": "건강을 위한 작은 선택들이 쌓여 건강한 노후를 만들어요."
      }
    ],
    "귀농탐색": [
      {
        "감정공감": "새로운 삶을 꿈꾸면서도 두려운 그 마음, 용기 있는 고민이에요.",
        "상황분석": "귀농은 단순한 이사가 아니라 삶의 방식을 바꾸는 큰 결정이에요. 충분히 탐색하고 준비할 시간이 필요해요.",
        "관점전환": "가족이 반대하는 건 걱정되어서예요. 실제 체험을 함께 해보면 가족도 조금씩 마음이 열릴 거예요.",
        "행동제안": "이번 주말 귀농귀촌 기초 체험 프로그램에 혼자라도 한 번 가보세요.",
        "희망메시지": "꿈을 꾸는 사람이 결국 새로운 삶을 만들어요. 응원해요."
      },
      {
        "감정공감": "도시의 삶에서 벗어나 자연 속에서 살고 싶다는 그 갈망, 충분히 이해해요.",
        "상황분석": "귀농귀촌에 대한 관심이 높아지는 이유가 있어요. 자연과 함께하는 삶이 주는 치유의 힘은 과학적으로도 입증되어 있어요.",
        "관점전환": "귀농을 꿈꾼다면 이미 준비가 시작된 거예요. 마음이 준비되면 길도 보여요.",
        "행동제안": "귀농 관련 커뮤니티나 블로그를 찾아보세요. 이미 귀농한 분들의 경험담이 현실적인 준비에 도움이 돼요.",
        "희망메시지": "자연으로 돌아가고 싶은 마음은 인간 본연의 치유 본능이에요."
      },
      {
        "감정공감": "농사와 자연 속 삶을 꿈꾸지만 현실적인 걱정들이 발목을 잡는 그 마음, 이해해요.",
        "상황분석": "귀농은 철저한 준비가 필요한 큰 결정이에요. 하지만 준비할수록 가능성도 높아져요.",
        "관점전환": "귀농을 선택한 분들 중 많은 분들이 '더 일찍 할걸'이라고 해요. 두려움보다 준비가 답이에요.",
        "행동제안": "귀농 체험 프로그램에 참여해서 실제로 경험해보세요. 해보고 나서 결정해도 늦지 않아요.",
        "희망메시지": "새로운 삶을 꿈꾸는 용기 자체가 이미 특별한 힘이에요."
      }
    ],
    "미래불안": [
      {
        "감정공감": "앞으로의 삶에 대한 불안, 50대라면 더욱 선명하게 느껴지실 거예요.",
        "상황분석": "50대의 미래 불안은 준비 부족이 아니라 새로운 챕터를 앞둔 자연스러운 감정이에요.",
        "관점전환": "10년 후의 당신이 지금 이 고민을 돌아본다면, 이 시간이 전환점이 되었다고 말할 거예요.",
        "행동제안": "오늘 작은 것 하나만 결정해보세요. 작은 결정들이 쌓여 방향이 만들어져요.",
        "희망메시지": "불안은 변화의 시작이에요. 지금 고민하는 것 자체가 이미 준비하고 있다는 증거예요."
      },
      {
        "감정공감": "남은 삶에 대한 막막함, 아직 하고 싶은 게 많은데 시간이 부족할 것 같은 그 불안, 느껴져요.",
        "상황분석": "50대는 통계적으로 인생의 절반 지점이에요. 남은 반이 여전히 엄청나게 많아요.",
        "관점전환": "지금까지의 경험이 앞으로의 삶을 더 지혜롭게 만들어줄 거예요. 50대의 미래는 20대와는 다른 풍요로움이 있어요.",
        "행동제안": "버킷리스트를 만들어보세요. 죽기 전에 하고 싶은 것들을 적다 보면 미래가 설레기 시작할 거예요.",
        "희망메시지": "50대는 인생의 황금기를 시작하는 나이예요."
      },
      {
        "감정공감": "노후가 걱정되고 준비가 부족한 것 같은 그 불안함, 충분히 이해해요.",
        "상황분석": "노후 불안은 재정적인 부분만이 아니에요. 건강, 관계, 의미 등 다양한 요소가 복합적으로 작용해요.",
        "관점전환": "완벽한 노후 준비는 없어요. 하지만 지금부터 하나씩 챙겨나가면 충분히 괜찮아질 수 있어요.",
        "행동제안": "재정, 건강, 관계 세 가지 중 가장 시급한 것 하나만 이번 달 집중해보세요.",
        "희망메시지": "준비하는 오늘이 더 나은 내일을 만들어요. 지금 시작이 충분해요."
      }
    ],
    "자식걱정": [
      {
        "감정공감": "다 큰 자식이라도 항상 물가에 내놓은 아이처럼 걱정되는 그 마음, 충분히 공감합니다.",
        "상황분석": "50대는 자녀가 사회생활을 시작하거나 독립을 준비하는 과도기예요. 지켜봐야 하는 입장이 되면서 불안이 더 커질 수 있어요.",
        "관점전환": "자녀는 부모님의 믿음을 먹고 자랍니다. 걱정보다는 믿음의 눈빛이 자녀에게 큰 힘이 돼요.",
        "행동제안": "자녀에 대한 걱정이 들 때마다, 그 마음을 조용한 응원으로 바꿔보세요.",
        "희망메시지": "지금까지 훌륭하게 키워내셨어요. 자녀도 자기만의 길을 잘 찾아갈 거예요."
      },
      {
        "감정공감": "자녀가 잘 되기를 바라는 마음에 잠 못 이루는 그 밤들, 얼마나 힘드실지 느껴져요.",
        "상황분석": "부모의 걱정은 끝이 없지만 자녀는 이미 어른이에요. 과도한 걱정은 때로 자녀에게 부담이 될 수 있어요.",
        "관점전환": "자녀를 믿는 것도 사랑이에요. 스스로 해결할 힘을 기를 수 있도록 조금씩 거리를 두는 것도 필요해요.",
        "행동제안": "자녀에게 '뭐가 필요하면 언제든 말해'라고 전달하고, 그 다음은 기다려주세요.",
        "희망메시지": "당신이 키운 자녀는 생각보다 훨씬 단단해요."
      },
      {
        "감정공감": "취업, 결혼, 독립... 자녀의 미래가 걱정되는 그 마음, 부모라면 당연한 감정이에요.",
        "상황분석": "요즘 세대는 이전 세대와 다른 환경 속에서 살고 있어요. 우리 때의 기준으로 자녀를 재단하면 둘 다 힘들어질 수 있어요.",
        "관점전환": "자녀가 살아가는 세상은 우리가 경험한 세상과 달라요. 그들의 방식을 신뢰해보는 것도 필요해요.",
        "행동제안": "자녀에게 걱정 대신 '어떤 도움이 필요해?'라고 물어보세요. 그 질문이 더 큰 힘이 돼요.",
        "희망메시지": "당신의 사랑이 자녀의 든든한 배경이 되고 있어요."
      }
    ]
  },
  "60대": {
    "은퇴적응": [
      {
        "감정공감": "오랫동안 일하다가 갑자기 멈추면 그 공백이 너무 크게 느껴지는 게 당연해요.",
        "상황분석": "은퇴 후 무기력함은 의지의 문제가 아니에요. 삶의 리듬과 역할이 바뀌면서 생기는 자연스러운 반응이에요.",
        "관점전환": "자녀들은 바빠서 연락을 못하는 거지, 부모님을 잊은 게 아니에요. 먼저 연락해서 솔직하게 말씀해보세요.",
        "행동제안": "오늘 자녀에게 먼저 전화해서 나 요즘 좀 심심하다고 말해보세요. 그 한 마디가 관계를 다시 열어요.",
        "희망메시지": "30년을 성실하게 살아오신 경험과 따뜻함은 은퇴 후에도 사라지지 않아요."
      },
      {
        "감정공감": "매일 아침 출근할 곳이 없다는 그 허전함, 익숙했던 일상이 사라진 그 공백감이 느껴져요.",
        "상황분석": "은퇴 후 첫 1~2년이 가장 어려운 시기예요. 새로운 리듬을 만드는 데 시간이 필요해요. 조급하게 생각하지 않아도 돼요.",
        "관점전환": "은퇴는 새로운 자유의 시작이에요. 이제 진짜 하고 싶었던 것들을 할 수 있는 시간이 생겼어요.",
        "행동제안": "매일 아침 작은 루틴 하나를 만들어보세요. 산책, 독서, 일기 쓰기 등 나만의 시간을 구조화해보세요.",
        "희망메시지": "새로운 리듬을 찾는 중이에요. 조금만 더 기다리면 당신만의 은퇴 생활이 만들어질 거예요."
      },
      {
        "감정공감": "쓸모없어진 것 같은 느낌, 사회에서 멀어지는 것 같은 그 소외감, 충분히 공감해요.",
        "상황분석": "은퇴 후 정체성 재구성은 많은 분들이 겪는 과정이에요. '나는 누구인가'에 대한 새로운 답을 찾아가는 여정이에요.",
        "관점전환": "지금까지 쌓아온 경험과 지혜는 은퇴 후에 더 빛날 수 있어요. 그것을 나눌 방법을 찾아보세요.",
        "행동제안": "지역 봉사 활동이나 시니어 동호회에 참여해보세요. 새로운 역할과 소속감을 찾을 수 있어요.",
        "희망메시지": "당신의 경험과 지혜는 세상에 여전히 필요해요."
      }
    ],
    "외로움": [
      {
        "감정공감": "혼자라는 느낌, 그 외로움이 얼마나 클지 충분히 이해해요.",
        "상황분석": "60대의 외로움은 사회적 관계망이 줄어드는 자연스러운 변화예요. 하지만 새로운 관계를 만드는 것도 충분히 가능해요.",
        "관점전환": "주변에 비슷한 마음을 가진 분들이 생각보다 많아요. 먼저 손을 내밀면 생각지 못한 따뜻한 인연을 만날 수 있어요.",
        "행동제안": "근처 실버 치유공간이나 원예 치료 프로그램에 한 번 참여해보세요.",
        "희망메시지": "새로운 인연은 나이와 관계없이 언제든 시작될 수 있어요."
      },
      {
        "감정공감": "가족들은 바쁘고 친구들도 연락이 뜸해진 그 쓸쓸함, 얼마나 힘드실지 느껴져요.",
        "상황분석": "60대의 외로움은 단순한 감정이 아니에요. 건강에도 영향을 줄 수 있어요. 적극적으로 해결 방법을 찾는 것이 중요해요.",
        "관점전환": "외로움을 느낀다는 것은 아직 연결에 대한 열망이 있다는 뜻이에요. 그 마음이 새로운 관계의 씨앗이 될 거예요.",
        "행동제안": "지역 문화센터나 노인복지관 프로그램에 참여해보세요. 같은 또래 분들과의 만남이 큰 위안이 돼요.",
        "희망메시지": "마음을 열면 새로운 따뜻한 인연이 기다리고 있어요."
      },
      {
        "감정공감": "사람들 속에 있어도 혼자인 것 같은 그 고독함, 60대라면 더욱 깊이 느껴질 수 있어요.",
        "상황분석": "나이가 들수록 관계망이 자연스럽게 좁아져요. 하지만 이것이 외로움의 이유가 될 필요는 없어요. 관계의 방식을 바꿀 수 있어요.",
        "관점전환": "깊이 있는 관계 하나가 수십 명의 지인보다 값져요. 지금이라도 한 명과 진짜 연결을 시작할 수 있어요.",
        "행동제안": "오랫동안 연락하지 못했던 소중한 분께 편지나 메시지를 써보세요. 그 마음이 전해질 거예요.",
        "희망메시지": "진심 어린 연결은 나이와 상관없이 언제나 가능해요."
      }
    ],
    "건강관리": [
      {
        "감정공감": "몸이 예전 같지 않다는 느낌, 그 불안함이 크게 느껴지실 거예요.",
        "상황분석": "60대 건강 관리는 치료보다 예방이 중요한 시기예요. 작은 습관들이 큰 차이를 만들어요.",
        "관점전환": "가족들은 당신이 건강하게 오래 곁에 있어주기를 가장 바라고 있어요.",
        "행동제안": "매일 아침 30분 가벼운 산책부터 시작해보세요. 꾸준함이 가장 좋은 건강 비결이에요.",
        "희망메시지": "지금부터 시작해도 충분해요. 오늘이 가장 빠른 날이에요."
      },
      {
        "감정공감": "이곳저곳 아프기 시작하는 몸을 보며 느끼는 불안과 서러움, 충분히 공감해요.",
        "상황분석": "60대의 건강 변화는 자연스러운 과정이에요. 중요한 것은 변화를 받아들이고 그에 맞게 생활을 조정하는 거예요.",
        "관점전환": "건강을 위해 무언가 하려는 마음 자체가 이미 건강의 증거예요. 그 의지가 있는 한 잘 지내실 수 있어요.",
        "행동제안": "주치의와 정기적으로 상담하면서 내 몸 상태를 정확히 파악하고 그에 맞는 생활을 해보세요.",
        "희망메시지": "건강을 챙기는 당신의 노력이 더 좋은 내일을 만들고 있어요."
      },
      {
        "감정공감": "건강 걱정에 잠 못 이루는 밤들, 그 불안함이 얼마나 클지 느껴져요.",
        "상황분석": "60대는 적절한 운동과 영양, 충분한 휴식이 가장 중요한 시기예요. 무리하지 않는 것이 핵심이에요.",
        "관점전환": "건강을 유지하는 것이 가족에 대한 가장 큰 선물이에요. 나를 위한 건강 관리가 가족을 위한 일이에요.",
        "행동제안": "오늘 가볍게 할 수 있는 스트레칭이나 체조를 10분만 해보세요. 무리하지 않아도 돼요.",
        "희망메시지": "건강하게 오래 사시는 것이 가족에게 가장 큰 행복이에요."
      }
    ],
    "가족관계": [
      {
        "감정공감": "가족과의 관계에서 느끼는 서운함, 오랜 시간 쌓인 감정이라 더 클 거예요.",
        "상황분석": "세대가 달라지면 소통 방식도 달라져요. 서로의 방식이 다를 뿐 사랑이 없는 게 아니에요.",
        "관점전환": "자녀 눈에 부모님은 여전히 가장 소중한 존재예요. 표현이 서툴러서 그렇지 마음은 항상 곁에 있어요.",
        "행동제안": "오늘 자녀에게 먼저 짧은 문자 하나 보내보세요. 기다리지 말고 먼저 다가가보세요.",
        "희망메시지": "가족의 사랑은 표현 방식이 달라도 변하지 않아요."
      },
      {
        "감정공감": "열심히 키웠는데 이제는 멀게 느껴지는 자녀들, 그 서운함과 외로움이 얼마나 클지 느껴져요.",
        "상황분석": "자녀들이 자신의 삶을 살아가는 것은 당연한 일이에요. 하지만 그 과정에서 부모는 소외감을 느낄 수 있어요.",
        "관점전환": "자녀들의 독립은 잘 키운 증거예요. 그들의 삶을 응원하는 것이 가장 큰 사랑이에요.",
        "행동제안": "자녀들과 정기적인 만남이나 연락 루틴을 만들어보세요. 자연스럽게 제안해보세요.",
        "희망메시지": "당신의 사랑이 자녀들의 든든한 뿌리가 되고 있어요."
      },
      {
        "감정공감": "배우자와의 관계에서 느끼는 갈등이나 거리감, 오랜 세월이 지나도 쉽지 않은 그 마음 느껴져요.",
        "상황분석": "60대 부부 관계는 은퇴, 자녀 독립 등 큰 변화 속에서 새로운 균형을 찾아야 하는 시기예요.",
        "관점전환": "오랜 세월을 함께한 배우자는 그 누구보다 소중한 존재예요. 서로의 다름을 인정하는 것이 더 좋은 관계의 시작이에요.",
        "행동제안": "오늘 배우자에게 고마웠던 일 하나를 말해보세요. 작은 감사 표현이 관계를 따뜻하게 해요.",
        "희망메시지": "함께 나이 들어가는 것이 인생 최고의 선물이에요."
      }
    ],
    "삶의의미": [
      {
        "감정공감": "살아온 날들을 돌아보며 의미를 찾고 싶은 마음, 깊고 소중한 고민이에요.",
        "상황분석": "60대는 삶을 돌아보고 의미를 재정립하는 중요한 시기예요. 이런 고민을 하는 것 자체가 성숙한 삶의 증거예요.",
        "관점전환": "당신이 살아온 삶 속에서 누군가에게 도움이 된 순간들을 떠올려보세요. 그 순간들이 모여 당신만의 의미가 됩니다.",
        "행동제안": "오늘 감사한 일 3가지를 적어보세요. 작은 것들 속에서 삶의 의미를 발견할 수 있어요.",
        "희망메시지": "살아온 모든 순간이 당신만의 소중한 이야기예요. 그 이야기는 계속되고 있어요."
      },
      {
        "감정공감": "이제 뭘 위해 살아야 하나 싶은 그 막막함, 60대라면 깊이 느껴지실 수 있어요.",
        "상황분석": "삶의 의미는 큰 것에서만 오지 않아요. 일상의 작은 기쁨들이 모여 의미 있는 삶을 만들어요.",
        "관점전환": "당신이 살아온 방식 자체가 이미 다음 세대에 영향을 주고 있어요. 보이지 않는 곳에서도 당신의 삶은 의미를 만들고 있어요.",
        "행동제안": "손자녀나 젊은 세대에게 당신의 경험을 나눠보세요. 그 이야기가 누군가에게 큰 힘이 될 거예요.",
        "희망메시지": "당신의 삶 자체가 다음 세대에게 보내는 가장 아름다운 메시지예요."
      },
      {
        "감정공감": "이만큼 살았는데 남은 건 뭔가, 앞으로 무엇을 위해 살아야 하나 싶은 그 질문이 무겁게 느껴지죠.",
        "상황분석": "삶의 의미에 대한 질문은 깊이 있게 살아온 사람들만이 할 수 있는 질문이에요. 그 질문 자체가 아름다워요.",
        "관점전환": "의미는 찾는 것이 아니라 만드는 것이에요. 지금 이 순간에도 새로운 의미를 만들 수 있어요.",
        "행동제안": "오늘 하루 누군가에게 작은 도움을 베풀어보세요. 그 순간에서 삶의 의미를 느낄 수 있어요.",
        "희망메시지": "살아있는 매 순간이 의미예요. 당신은 충분히 의미 있는 삶을 살고 있어요."
      }
    ],
    "자식걱정": [
      {
        "감정공감": "품을 떠난 자식 걱정에 밤잠을 설치시는 그 따뜻하고 애틋한 마음, 충분히 이해합니다.",
        "상황분석": "60대가 되면 자녀들도 어엿한 어른이 되어 각자의 가정을 꾸리는 시기예요. 걱정은 당연하지만 때로는 내려놓는 연습도 필요해요.",
        "관점전환": "이제는 자식 걱정은 조금 내려놓고, 그동안 고생한 나 자신을 위한 시간을 가져보는 건 어떨까요?",
        "행동제안": "오늘 자녀에게 걱정 대신 믿는다, 사랑한다는 짧은 메시지를 먼저 보내보세요.",
        "희망메시지": "자녀분은 부모님의 사랑 속에서 단단하게 자랐어요. 이제 믿고 지켜봐 주셔도 괜찮아요."
      },
      {
        "감정공감": "자녀들 걱정에 내 몸도 못 챙기게 되는 그 마음, 부모라면 누구나 그렇겠죠.",
        "상황분석": "자녀를 걱정하는 것은 사랑의 표현이지만, 과도한 걱정은 본인 건강에도 영향을 줄 수 있어요.",
        "관점전환": "자녀들도 나름의 방법으로 잘 살아가고 있어요. 부모님의 믿음이 그들에게 가장 큰 힘이 돼요.",
        "행동제안": "자녀 걱정이 들 때마다 그 에너지를 본인을 위한 활동에 써보세요. 내가 건강해야 자녀에게도 힘이 될 수 있어요.",
        "희망메시지": "당신이 잘 살아가는 것이 자녀들에게 가장 큰 선물이에요."
      },
      {
        "감정공감": "평생 자녀를 위해 살았는데 이제는 그 자녀가 잘 살고 있는지 걱정되는 그 마음, 정말 따뜻하고 고마운 마음이에요.",
        "상황분석": "부모의 걱정은 끝이 없지만 자녀들은 생각보다 훨씬 단단해요. 당신이 키운 방식대로 잘 살아가고 있을 거예요.",
        "관점전환": "이제는 자녀의 행복이 곧 나의 행복이라고 생각하는 것에서 나의 행복이 곧 자녀의 행복이라는 생각으로 바꿔보세요.",
        "행동제안": "오늘 자녀에게 연락하되, 걱정이 아닌 안부와 사랑을 전해보세요.",
        "희망메시지": "당신의 사랑이 자녀들의 평생 든든한 울타리가 되고 있어요."
      }
    ]
  }
}
